linkedpy/__init__.py
linkedpy/list.py
linkedpy/node.py
linkedpy-0.1.0.dist-info/METADATA
linkedpy-0.1.0.dist-info/WHEEL
linkedpy-0.1.0.dist-info/top_level.txt
linkedpy-0.1.0.dist-info/RECORD
