Metadata-Version: 2.1
Name: linkedpy
Version: 0.1.0
Summary: Python implementation of a default List using linked list
Home-page: https://github.com/hardope/linkedpy
Author: Opeoluwa Adeyeri
Author-email: adeyeriopeoluwa05@gmail.com
Classifier: Programming Language :: Python :: 3
Classifier: License :: OSI Approved :: MIT License
Classifier: Operating System :: OS Independent
